MANIFEST.in
MIT_LICENSE
README.md
requirements.txt
setup.cfg
setup.py
metrics.pytest_cov.egg-info/PKG-INFO
metrics.pytest_cov.egg-info/SOURCES.txt
metrics.pytest_cov.egg-info/dependency_links.txt
metrics.pytest_cov.egg-info/entry_points.txt
metrics.pytest_cov.egg-info/requires.txt
metrics.pytest_cov.egg-info/top_level.txt
metrics_pytest_cov/__init__.py
metrics_pytest_cov/cov.py